stardist/__init__.py
stardist/big.py
stardist/bioimageio_utils.py
stardist/matching.py
stardist/nms.py
stardist/rays3d.py
stardist/sample_patches.py
stardist/utils.py
stardist/version.py
stardist/data/__init__.py
stardist/data/images/histo.jpg
stardist/data/images/img2d.tif
stardist/data/images/img3d.tif
stardist/data/images/mask2d.tif
stardist/data/images/mask3d.tif
stardist/geometry/__init__.py
stardist/geometry/geom2d.py
stardist/geometry/geom3d.py
stardist/kernels/stardist2d.cl
stardist/kernels/stardist3d.cl
stardist/lib/stardist2d.cp36-win_amd64.pyd
stardist/lib/stardist3d.cp36-win_amd64.pyd
stardist/models/__init__.py
stardist/models/base.py
stardist/models/model2d.py
stardist/models/model3d.py
stardist/plot/__init__.py
stardist/plot/plot.py
stardist/plot/render.py
stardist/scripts/__init__.py
stardist/scripts/predict2d.py
stardist/scripts/predict3d.py
stardist_sparse-0.8.3.dist-info/LICENSE.txt
stardist_sparse-0.8.3.dist-info/METADATA
stardist_sparse-0.8.3.dist-info/WHEEL
stardist_sparse-0.8.3.dist-info/entry_points.txt
stardist_sparse-0.8.3.dist-info/top_level.txt
stardist_sparse-0.8.3.dist-info/RECORD
