Metadata-Version: 2.1
Name: stardist-sparse
Version: 0.8.3
Summary: StarDist - Object Detection with Star-convex Shapes
Home-page: https://github.com/ksugar/stardist-sparse
Author: Ko Sugawara, Uwe Schmidt, Martin Weigert
Author-email: ko.sugawara@riken.jp, research@uweschmidt.org, martin.weigert@epfl.ch
License: BSD-3-Clause
Platform: UNKNOWN
Classifier: Development Status :: 4 - Beta
Classifier: Intended Audience :: Science/Research
Classifier: Topic :: Scientific/Engineering
Classifier: License :: OSI Approved :: BSD License
Classifier: Operating System :: OS Independent
Classifier: Programming Language :: Python :: 3.6
Classifier: Programming Language :: Python :: 3.7
Classifier: Programming Language :: Python :: 3.8
Classifier: Programming Language :: Python :: 3.9
Classifier: Programming Language :: Python :: 3.10
Requires-Python: >=3.6
License-File: LICENSE.txt
Requires-Dist: csbdeep (>=0.6.3)
Requires-Dist: scikit-image
Requires-Dist: numba
Requires-Dist: imageio
Provides-Extra: bioimageio
Requires-Dist: bioimageio.core (>=0.5.0) ; extra == 'bioimageio'
Requires-Dist: importlib-metadata ; extra == 'bioimageio'
Provides-Extra: test
Requires-Dist: pytest ; extra == 'test'
Provides-Extra: tf1
Requires-Dist: csbdeep[tf1] (>=0.6.3) ; extra == 'tf1'
